{
  "PackageData": [
    {
      "Row": [
        {
          "SchemaColumnUId": "ae0e45ca-c495-4fe7-a39d-3ab7278e1617",
          "ColumnName": "Id",
          "Value": "b8e2bbe8-cba8-4b67-b4e9-48f8047ef179"
        },
        {
          "SchemaColumnUId": "736c30a7-c0ec-4fa9-b034-2552b319b633",
          "ColumnName": "Name",
          "Value": "1. Sale"
        },
        {
          "SchemaColumnUId": "9e53fd7c-dde4-4502-a64c-b9e34148108b",
          "ColumnName": "Description",
          "Value": ""
        }
      ]
    },
    {
      "Row": [
        {
          "SchemaColumnUId": "ae0e45ca-c495-4fe7-a39d-3ab7278e1617",
          "ColumnName": "Id",
          "Value": "dcbae2ff-5652-46eb-8c3a-265185099ef1"
        },
        {
          "SchemaColumnUId": "736c30a7-c0ec-4fa9-b034-2552b319b633",
          "ColumnName": "Name",
          "Value": "2. Rental"
        },
        {
          "SchemaColumnUId": "9e53fd7c-dde4-4502-a64c-b9e34148108b",
          "ColumnName": "Description",
          "Value": ""
        }
      ]
    }
  ]
}